odoo/addons/supplier_calendar/README.rst
odoo/addons/supplier_calendar/__init__.py
odoo/addons/supplier_calendar/__manifest__.py
odoo/addons/supplier_calendar/i18n/es.po
odoo/addons/supplier_calendar/i18n/it.po
odoo/addons/supplier_calendar/i18n/pt_BR.po
odoo/addons/supplier_calendar/i18n/supplier_calendar.pot
odoo/addons/supplier_calendar/models/__init__.py
odoo/addons/supplier_calendar/models/product.py
odoo/addons/supplier_calendar/models/purchase.py
odoo/addons/supplier_calendar/models/res_partner.py
odoo/addons/supplier_calendar/models/stock_rule.py
odoo/addons/supplier_calendar/readme/CONFIGURE.md
odoo/addons/supplier_calendar/readme/CONTRIBUTORS.md
odoo/addons/supplier_calendar/readme/DESCRIPTION.md
odoo/addons/supplier_calendar/readme/USAGE.md
odoo/addons/supplier_calendar/static/description/icon.png
odoo/addons/supplier_calendar/static/description/index.html
odoo/addons/supplier_calendar/tests/__init__.py
odoo/addons/supplier_calendar/tests/test_supplier_calendar.py
odoo/addons/supplier_calendar/views/product_view.xml
odoo/addons/supplier_calendar/views/res_partner_view.xml
odoo_addon_supplier_calendar-18.0.1.0.0.3.dist-info/METADATA
odoo_addon_supplier_calendar-18.0.1.0.0.3.dist-info/WHEEL
odoo_addon_supplier_calendar-18.0.1.0.0.3.dist-info/top_level.txt
odoo_addon_supplier_calendar-18.0.1.0.0.3.dist-info/RECORD
